{
  "$schema": "http://adaptivecards.io/schemas/adaptive-card.json",
  "actions": [
    {
      "data": {
        "cardId": "MP-CARD-08",
        "flow": "meetingPrep",
        "nav": "back",
        "toCardId": "MP-CARD-02"
      },
      "title": "{{i18n:cards.mp_card_08_eu_data_residency_summary.actions.i0.title}}",
      "type": "Action.Submit"
    }
  ],
  "body": [
    {
      "color": "Dark",
      "size": "Large",
      "text": "{{i18n:cards.mp_card_08_eu_data_residency_summary.body.i0.text}}",
      "type": "TextBlock",
      "weight": "Bolder",
      "wrap": true
    },
    {
      "color": "Dark",
      "text": "{{i18n:cards.mp_card_08_eu_data_residency_summary.body.i1.text}}",
      "type": "TextBlock",
      "wrap": true
    },
    {
      "color": "Dark",
      "spacing": "Small",
      "text": "{{i18n:cards.mp_card_08_eu_data_residency_summary.body.i2.text}}",
      "type": "TextBlock",
      "wrap": true
    },
    {
      "color": "Dark",
      "spacing": "Medium",
      "text": "{{i18n:cards.mp_card_08_eu_data_residency_summary.body.i3.text}}",
      "type": "TextBlock",
      "weight": "Bolder",
      "wrap": true
    },
    {
      "bleed": true,
      "items": [
        {
          "color": "Light",
          "text": "{{i18n:cards.mp_card_08_eu_data_residency_summary.body.i4.items.i0.text}}",
          "type": "TextBlock",
          "weight": "Bolder",
          "wrap": true
        }
      ],
      "selectAction": {
        "targetElements": [
          "mp08_s1"
        ],
        "type": "Action.ToggleVisibility"
      },
      "spacing": "Small",
      "style": "accent",
      "type": "Container"
    },
    {
      "id": "mp08_s1",
      "isVisible": false,
      "items": [
        {
          "color": "Dark",
          "text": "{{i18n:cards.mp_card_08_eu_data_residency_summary.body.i5.items.i0.text}}",
          "type": "TextBlock",
          "wrap": true
        }
      ],
      "spacing": "Small",
      "type": "Container"
    },
    {
      "bleed": true,
      "items": [
        {
          "color": "Light",
          "text": "{{i18n:cards.mp_card_08_eu_data_residency_summary.body.i6.items.i0.text}}",
          "type": "TextBlock",
          "weight": "Bolder",
          "wrap": true
        }
      ],
      "selectAction": {
        "targetElements": [
          "mp08_s2"
        ],
        "type": "Action.ToggleVisibility"
      },
      "spacing": "Small",
      "style": "accent",
      "type": "Container"
    },
    {
      "id": "mp08_s2",
      "isVisible": false,
      "items": [
        {
          "color": "Dark",
          "text": "{{i18n:cards.mp_card_08_eu_data_residency_summary.body.i7.items.i0.text}}",
          "type": "TextBlock",
          "wrap": true
        }
      ],
      "spacing": "Small",
      "type": "Container"
    },
    {
      "bleed": true,
      "items": [
        {
          "color": "Light",
          "text": "{{i18n:cards.mp_card_08_eu_data_residency_summary.body.i8.items.i0.text}}",
          "type": "TextBlock",
          "weight": "Bolder",
          "wrap": true
        }
      ],
      "selectAction": {
        "targetElements": [
          "mp08_s3"
        ],
        "type": "Action.ToggleVisibility"
      },
      "spacing": "Small",
      "style": "accent",
      "type": "Container"
    },
    {
      "id": "mp08_s3",
      "isVisible": false,
      "items": [
        {
          "color": "Dark",
          "text": "{{i18n:cards.mp_card_08_eu_data_residency_summary.body.i9.items.i0.text}}",
          "type": "TextBlock",
          "wrap": true
        }
      ],
      "spacing": "Small",
      "type": "Container"
    },
    {
      "bleed": true,
      "items": [
        {
          "color": "Light",
          "text": "{{i18n:cards.mp_card_08_eu_data_residency_summary.body.i10.items.i0.text}}",
          "type": "TextBlock",
          "weight": "Bolder",
          "wrap": true
        }
      ],
      "selectAction": {
        "targetElements": [
          "mp08_s4"
        ],
        "type": "Action.ToggleVisibility"
      },
      "spacing": "Small",
      "style": "accent",
      "type": "Container"
    },
    {
      "id": "mp08_s4",
      "isVisible": false,
      "items": [
        {
          "color": "Dark",
          "text": "{{i18n:cards.mp_card_08_eu_data_residency_summary.body.i11.items.i0.text}}",
          "type": "TextBlock",
          "wrap": true
        }
      ],
      "spacing": "Small",
      "type": "Container"
    },
    {
      "bleed": true,
      "items": [
        {
          "color": "Light",
          "text": "{{i18n:cards.mp_card_08_eu_data_residency_summary.body.i12.items.i0.text}}",
          "type": "TextBlock",
          "weight": "Bolder",
          "wrap": true
        }
      ],
      "selectAction": {
        "targetElements": [
          "mp08_s5"
        ],
        "type": "Action.ToggleVisibility"
      },
      "spacing": "Small",
      "style": "accent",
      "type": "Container"
    },
    {
      "id": "mp08_s5",
      "isVisible": false,
      "items": [
        {
          "color": "Dark",
          "text": "{{i18n:cards.mp_card_08_eu_data_residency_summary.body.i13.items.i0.text}}",
          "type": "TextBlock",
          "wrap": true
        }
      ],
      "spacing": "Small",
      "type": "Container"
    },
    {
      "bleed": true,
      "items": [
        {
          "color": "Light",
          "text": "{{i18n:cards.mp_card_08_eu_data_residency_summary.body.i14.items.i0.text}}",
          "type": "TextBlock",
          "weight": "Bolder",
          "wrap": true
        }
      ],
      "selectAction": {
        "targetElements": [
          "mp08_s6"
        ],
        "type": "Action.ToggleVisibility"
      },
      "spacing": "Small",
      "style": "accent",
      "type": "Container"
    },
    {
      "id": "mp08_s6",
      "isVisible": false,
      "items": [
        {
          "color": "Dark",
          "text": "{{i18n:cards.mp_card_08_eu_data_residency_summary.body.i15.items.i0.text}}",
          "type": "TextBlock",
          "wrap": true
        }
      ],
      "spacing": "Small",
      "type": "Container"
    }
  ],
  "metadata": {
    "_lovableFlow": {
      "cardKey": "MP-CARD-08_eu_data_residency_summary",
      "implicitOutgoing": [],
      "incoming": [
        {
          "from": "MP-CARD-02_meeting_prep",
          "path": "body/[5]/selectAction/data/routeToCardId",
          "via": "key:routeToCardId"
        },
        {
          "from": "MP-CARD-02_meeting_prep",
          "path": "body/[5]/selectAction",
          "via": "action.data:routeToCardId"
        }
      ],
      "incomingResolved": [
        {
          "condition": "explicit:routeToCardId",
          "from": "MP-CARD-02_meeting_prep",
          "path": "body/[5]/selectAction"
        }
      ],
      "outgoing": [
        {
          "path": "actions/[0]/data/toCardId",
          "to": "MP-CARD-02_meeting_prep",
          "via": "key:toCardId"
        },
        {
          "path": "actions/[0]",
          "to": "MP-CARD-02_meeting_prep",
          "via": "action.data:toCardId"
        }
      ],
      "outgoingOpenUrl": [],
      "outgoingResolved": [
        {
          "condition": "explicit:toCardId",
          "path": "actions/[0]",
          "to": "MP-CARD-02_meeting_prep",
          "type": "navigate"
        }
      ],
      "stillAmbiguous": []
    }
  },
  "type": "AdaptiveCard",
  "version": "1.3"
}
